tableprinter/__init__.py
tableprinter/ascii.py
tableprinter/html.py
tableprinter/latex.py
tableprinter/tabulator.py
tableprinter-0.3.1.dist-info/DESCRIPTION.rst
tableprinter-0.3.1.dist-info/METADATA
tableprinter-0.3.1.dist-info/RECORD
tableprinter-0.3.1.dist-info/WHEEL
tableprinter-0.3.1.dist-info/metadata.json
tableprinter-0.3.1.dist-info/top_level.txt
