Metadata-Version: 2.0
Name: tableprinter
Version: 0.3.1
Summary: Yet another python table printer. This one outputs your tables to HTML, LaTeX, Unicode and ASCII. It can deal with hierarchical rows / columns, output in color, ...
Home-page: https://github.com/tinloaf/tableprinter
Author: Lukas Barth
Author-email: pypi@mbox.tinloaf.de
License: MIT
Keywords: pretty-printing printing table tabular
Platform: UNKNOWN
Classifier: Development Status :: 4 - Beta
Classifier: Intended Audience :: Developers
Classifier: License :: OSI Approved :: MIT License
Classifier: Programming Language :: Python :: 3
Classifier: Topic :: Software Development :: Libraries :: Python Modules
